[{"OnetrustActiveGroups":",,","event":"OneTrustLoaded"},{"OptanonActiveGroups":",,","event":"OptanonLoaded"},{"OnetrustActiveGroups":",C0001,","event":"OneTrustLoaded"},{"OptanonActiveGroups":",C0001,","event":"OptanonLoaded"},{"OnetrustActiveGroups":",C0001,","event":"OneTrustGroupsUpdated"},{"event":"gtm.js","gtm.start":1720722145921},["js",{}],["set","developer_id.dMDhkMT",true],["config",""],{"clickText":"Find Care > Find a Doctor | 2","event":"e_navigationClick","linkType":"link","navigationType":"footer"}]