[{"OnetrustActiveGroups":",,","event":"OneTrustLoaded","gtm.uniqueEventId":1},{"OptanonActiveGroups":",,","event":"OptanonLoaded","gtm.uniqueEventId":2},{"OnetrustActiveGroups":",,","event":"OneTrustLoaded","gtm.uniqueEventId":3},{"OptanonActiveGroups":",,","event":"OptanonLoaded","gtm.uniqueEventId":4},{"OnetrustActiveGroups":",,","event":"OneTrustGroupsUpdated","gtm.uniqueEventId":5},{"event":"gtm.js","gtm.start":1698953305396,"gtm.uniqueEventId":6},{"event":"gtm.dom","gtm.uniqueEventId":8},{"event":"gtm.elementVisibility","gtm.element":{"element-6066-11e4-a52e-4f735466cecf":"D810268C670842CB5770E24AD98DB0F8_element_3047"},"gtm.elementClasses":"visually-hidden","gtm.elementId":"","gtm.elementTarget":"","gtm.elementUrl":"","gtm.triggers":"59547834_285","gtm.uniqueEventId":9,"gtm.visibleFirstTime":72,"gtm.visibleLastTime":72,"gtm.visibleRatio":100,"gtm.visibleTime":0},{"event":"gtm.elementVisibility","gtm.element":{"element-6066-11e4-a52e-4f735466cecf":"D810268C670842CB5770E24AD98DB0F8_element_3048"},"gtm.elementClasses":"visually-hidden","gtm.elementId":"","gtm.elementTarget":"","gtm.elementUrl":"","gtm.triggers":"59547834_285","gtm.uniqueEventId":10,"gtm.visibleFirstTime":73,"gtm.visibleLastTime":73,"gtm.visibleRatio":100,"gtm.visibleTime":0},{"event":"gtm.elementVisibility","gtm.element":{"element-6066-11e4-a52e-4f735466cecf":"D810268C670842CB5770E24AD98DB0F8_element_3049"},"gtm.elementClasses":"mf-text-title-1-serif","gtm.elementId":"","gtm.elementTarget":"","gtm.elementUrl":"","gtm.triggers":"59547834_285","gtm.uniqueEventId":11,"gtm.visibleFirstTime":73,"gtm.visibleLastTime":73,"gtm.visibleRatio":100,"gtm.visibleTime":0},{"event":"gtm.load","gtm.uniqueEventId":13},{"event":"gtm.scrollDepth","gtm.scrollDirection":"vertical","gtm.scrollThreshold":5,"gtm.scrollUnits":"percent","gtm.triggers":"59547834_180","gtm.uniqueEventId":14},{"event":"gtm.scrollDepth","gtm.scrollDirection":"vertical","gtm.scrollThreshold":10,"gtm.scrollUnits":"percent","gtm.triggers":"59547834_180","gtm.uniqueEventId":16},{"event":"gtm.scrollDepth","gtm.scrollDirection":"vertical","gtm.scrollThreshold":25,"gtm.scrollUnits":"percent","gtm.triggers":"59547834_180","gtm.uniqueEventId":18},{"event":"gtm.elementVisibility","gtm.element":{"element-6066-11e4-a52e-4f735466cecf":"D810268C670842CB5770E24AD98DB0F8_element_3050"},"gtm.elementClasses":"","gtm.elementId":"","gtm.elementTarget":"","gtm.elementUrl":"","gtm.triggers":"59547834_282","gtm.uniqueEventId":20,"gtm.visibleFirstTime":212,"gtm.visibleLastTime":212,"gtm.visibleRatio":100,"gtm.visibleTime":0},{"event":"gtm.scrollDepth","gtm.scrollDirection":"vertical","gtm.scrollThreshold":50,"gtm.scrollUnits":"percent","gtm.triggers":"59547834_180","gtm.uniqueEventId":21},{"event":"gtm.click","gtm.element":{"element-6066-11e4-a52e-4f735466cecf":"D810268C670842CB5770E24AD98DB0F8_element_3039"},"gtm.elementClasses":"mf-button__ripple","gtm.elementId":"","gtm.elementTarget":"","gtm.elementUrl":"","gtm.uniqueEventId":23},{"clickText":"Section Header Button","componentType":"section header","event":"e_componentClick","gtm.uniqueEventId":25,"itemTitle":"Section Header Headline","linkType":"button","pageSlot":"1"},{"event":"gtm.linkClick","eventCallback":{},"eventTimeout":2000,"gtm.element":{"element-6066-11e4-a52e-4f735466cecf":"D810268C670842CB5770E24AD98DB0F8_element_3038"},"gtm.elementClasses":"mf-button mf-button--site-montefiore mf-button--primary mf-button--base mf-button--rounded","gtm.elementId":"","gtm.elementTarget":"_blank","gtm.elementText":"Section Header Button","gtm.elementUrl":"https://google.com/","gtm.triggers":"59547834_37,59547834_62,59547834_82,59547834_114,59547834_132,59547834_235,59547834_236,59547834_254,59547834_259,59547834_263,59547834_303,59547834_304,59547834_305,59547834_312,59547834_322,59547834_325","gtm.uniqueEventId":51,"gtm.willOpenInNewWindow":true},{"clickSlot":null,"clickText":null,"clinicalAge":null,"clinicalCat1":null,"clinicalCat2":null,"clinicalKeyword":null,"componentType":null,"itemTitle":null,"linkType":null,"pageSlot":null,"phoneNumber":null}]